{"obokekyo":{"title":"Obokekyo","panoid":"7yQAmgJphjAtG_XmcoTOhQ","lat":"33.881836","lng":"133.760136","pitch":"-9.14","heading":"1.53"},"mount-tsurugi":{"title":"Mount Tsurugi","panoid":"-pGEAoPClD_qB9kpsIE_Eg","lat":"33.853772","lng":"134.094416","pitch":"5.72","heading":"33.02"},"soya-no-kazura-bridge":{"title":"Soya no Kazura bridge","panoid":"mb3WHPRuDprssXEaVmyFfg","lat":"33.874935","lng":"133.834533","pitch":"0.0","heading":"135.0"},"parent":{"title":"Nishi-Awa, Mt. Tsurugi and The Yoshino River Tourism Zone","panoid":"7yQAmgJphjAtG_XmcoTOhQ","lat":"33.881836","lng":"133.760136","pitch":"-9.14","heading":"1.53","pano":"obokekyo"}}